YouxiYinqingKaifaRumenjiaochengCYuyanBianchengWang/README.md
YouxiYinqingKaifaRumenjiaochengCYuyanBianchengWang/__init__.py
YouxiYinqingKaifaRumenjiaochengCYuyanBianchengWang/__main__.py
YouxiYinqingKaifaRumenjiaochengCYuyanBianchengWang/file.epub
YouxiYinqingKaifaRumenjiaochengCYuyanBianchengWang/index.html
YouxiYinqingKaifaRumenjiaochengCYuyanBianchengWang/css/__init__.py
YouxiYinqingKaifaRumenjiaochengCYuyanBianchengWang/css/annotations.css
YouxiYinqingKaifaRumenjiaochengCYuyanBianchengWang/css/main.css
YouxiYinqingKaifaRumenjiaochengCYuyanBianchengWang/css/normalize.css
YouxiYinqingKaifaRumenjiaochengCYuyanBianchengWang/css/popup.css
YouxiYinqingKaifaRumenjiaochengCYuyanBianchengWang/font/__init__.py
YouxiYinqingKaifaRumenjiaochengCYuyanBianchengWang/font/fontello.eot
YouxiYinqingKaifaRumenjiaochengCYuyanBianchengWang/font/fontello.svg
YouxiYinqingKaifaRumenjiaochengCYuyanBianchengWang/font/fontello.ttf
YouxiYinqingKaifaRumenjiaochengCYuyanBianchengWang/font/fontello.woff
YouxiYinqingKaifaRumenjiaochengCYuyanBianchengWang/img/__init__.py
YouxiYinqingKaifaRumenjiaochengCYuyanBianchengWang/img/annotator-glyph-sprite.png
YouxiYinqingKaifaRumenjiaochengCYuyanBianchengWang/img/annotator-icon-sprite.png
YouxiYinqingKaifaRumenjiaochengCYuyanBianchengWang/img/apple-touch-icon.png
YouxiYinqingKaifaRumenjiaochengCYuyanBianchengWang/img/cancelfullscreen.png
YouxiYinqingKaifaRumenjiaochengCYuyanBianchengWang/img/close.png
YouxiYinqingKaifaRumenjiaochengCYuyanBianchengWang/img/fullscreen.png
YouxiYinqingKaifaRumenjiaochengCYuyanBianchengWang/img/loader.gif
YouxiYinqingKaifaRumenjiaochengCYuyanBianchengWang/img/menu-icon.png
YouxiYinqingKaifaRumenjiaochengCYuyanBianchengWang/img/save.png
YouxiYinqingKaifaRumenjiaochengCYuyanBianchengWang/img/saved.png
YouxiYinqingKaifaRumenjiaochengCYuyanBianchengWang/img/settings-s.png
YouxiYinqingKaifaRumenjiaochengCYuyanBianchengWang/img/settings.png
YouxiYinqingKaifaRumenjiaochengCYuyanBianchengWang/img/star.png
youxi_yinqing_kaifa_rumenjiaocheng_c_yuyan_biancheng_wang-2024.3.5.0.dist-info/METADATA
youxi_yinqing_kaifa_rumenjiaocheng_c_yuyan_biancheng_wang-2024.3.5.0.dist-info/WHEEL
youxi_yinqing_kaifa_rumenjiaocheng_c_yuyan_biancheng_wang-2024.3.5.0.dist-info/entry_points.txt
youxi_yinqing_kaifa_rumenjiaocheng_c_yuyan_biancheng_wang-2024.3.5.0.dist-info/top_level.txt
youxi_yinqing_kaifa_rumenjiaocheng_c_yuyan_biancheng_wang-2024.3.5.0.dist-info/RECORD
